google/__init__.py
google/adk/__init__.py
google/adk/nocode/__init__.py
google/adk/nocode/app.py
google/adk/nocode/cli.py
google/adk/nocode/ollama_integration.py
google/adk/nocode/static/css/styles.css
google/adk/nocode/static/js/app.js
google/adk/nocode/templates/index.html
google_adk_nocode-0.1.3.dist-info/METADATA
google_adk_nocode-0.1.3.dist-info/WHEEL
google_adk_nocode-0.1.3.dist-info/entry_points.txt
google_adk_nocode-0.1.3.dist-info/top_level.txt
google_adk_nocode-0.1.3.dist-info/RECORD
