Metadata-Version: 2.4
Name: google-adk-nocode
Version: 0.1.3
Summary: No-code interface for the Google Agent Development Kit with multi-tech stack support
Author: ADK Community
Author-email: ADK Community <example@example.com>
Project-URL: Homepage, https://github.com/abhishekkumar35/google-adk-nocode
Project-URL: Bug Tracker, https://github.com/abhishekkumar35/google-adk-nocode/issues
Project-URL: Funding, https://github.com/sponsors/abhishekkumar35
Classifier: Programming Language :: Python :: 3
Classifier: License :: OSI Approved :: Apache Software License
Classifier: Operating System :: OS Independent
Requires-Python: >=3.9
Requires-Dist: fastapi>=0.95.0
Requires-Dist: uvicorn>=0.21.1
Requires-Dist: jinja2>=3.1.2
Requires-Dist: pydantic>=2.0.0
Requires-Dist: requests>=2.28.0
Requires-Dist: python-multipart>=0.0.6
